docketpy/__init__.py
docketpy/base.py
docketpy/bigquery.py
docketpy/config.py
docketpy/core.py
docketpy/exceptions.py
docketpy/gcs.py
docketpy/mathx.py
docketpy/python.py
docketpy/cloud/__init__.py
docketpy/cloud/alibaba.py
docketpy/cloud/aws.py
docketpy/cloud/azure.py
docketpy/cloud/gcp.py
docketpy/cloud/oracle.py
docketpy/db/__init__.py
docketpy/db/create.py
docketpy/db/delete.py
docketpy/db/engine.py
docketpy/db/init.py
docketpy/db/models.py
docketpy/db/read.py
docketpy/db/test.py
docketpy/db/update.py
docketpy/db/wsinit.py
docketpy-2.1.2.dist-info/LICENSE
docketpy-2.1.2.dist-info/METADATA
docketpy-2.1.2.dist-info/WHEEL
docketpy-2.1.2.dist-info/top_level.txt
docketpy-2.1.2.dist-info/RECORD
