Metadata-Version: 2.1
Name: docketpy
Version: 2.1.2
Summary: Docket Python library
Author: VST
License: MIT
License-File: LICENSE
Requires-Dist: dill
Requires-Dist: redis
Requires-Dist: numpy
Requires-Dist: google-cloud-storage
Requires-Dist: google-cloud-bigquery
Requires-Dist: SQLAlchemy
Requires-Dist: sqlalchemy-utils
Requires-Dist: psycopg2-binary
